systemctl2mqtt/__init__.py
systemctl2mqtt/__main__.py
systemctl2mqtt/const.py
systemctl2mqtt/exceptions.py
systemctl2mqtt/helpers.py
systemctl2mqtt/py.typed
systemctl2mqtt/systemctl2mqtt.py
systemctl2mqtt/type_definitions.py
systemctl2mqtt-1.4.0.dist-info/licenses/LICENSE
systemctl2mqtt-1.4.0.dist-info/METADATA
systemctl2mqtt-1.4.0.dist-info/WHEEL
systemctl2mqtt-1.4.0.dist-info/entry_points.txt
systemctl2mqtt-1.4.0.dist-info/top_level.txt
systemctl2mqtt-1.4.0.dist-info/RECORD
