Metadata-Version: 2.4
Name: systemctl2mqtt
Version: 1.4.0
Summary: Send your systemctl stats and and events to mqtt and discovery them in home assistant.
Author-email: Cyrill Raccaud <cyrill.raccaud+pypi@gmail.com>
License: MIT License
Project-URL: Documentation, https://miaucl.github.io/systemctl2mqtt/
Project-URL: Source, https://github.com/miaucl/systemctl2mqtt
Project-URL: Issues, https://github.com/miaucl/systemctl2mqtt/issues
Keywords: systemctl,mqtt,paho,home-assistant,system-monitoring,discovery,iot
Classifier: Programming Language :: Python :: 3
Classifier: License :: OSI Approved :: MIT License
Classifier: Operating System :: OS Independent
Classifier: Intended Audience :: Information Technology
Classifier: Topic :: System :: Monitoring
Classifier: Topic :: System :: Logging
Classifier: Topic :: System :: Systems Administration
Requires-Python: >=3.11
License-File: LICENSE
Requires-Dist: paho-mqtt
Dynamic: license-file
